LICENSE
MANIFEST.in
README.md
setup.py
gears_eco/__init__.py
gears_eco/compiler.js
gears_eco/compiler.py
gears_eco.egg-info/PKG-INFO
gears_eco.egg-info/SOURCES.txt
gears_eco.egg-info/dependency_links.txt
gears_eco.egg-info/top_level.txt
gears_eco/node_modules/.bin/eco
gears_eco/node_modules/eco/.npmignore
gears_eco/node_modules/eco/LICENSE
gears_eco/node_modules/eco/README.md
gears_eco/node_modules/eco/Rakefile
gears_eco/node_modules/eco/eco-source-1.1.0.rc.1.gem
gears_eco/node_modules/eco/manual.html
gears_eco/node_modules/eco/package.json
gears_eco/node_modules/eco/bin/eco
gears_eco/node_modules/eco/dist/eco.html
gears_eco/node_modules/eco/dist/eco.js
gears_eco/node_modules/eco/lib/command.js
gears_eco/node_modules/eco/lib/compiler.js
gears_eco/node_modules/eco/lib/index.js
gears_eco/node_modules/eco/lib/preprocessor.js
gears_eco/node_modules/eco/lib/scanner.js
gears_eco/node_modules/eco/lib/util.js
gears_eco/node_modules/eco/node_modules/.bin/cake
gears_eco/node_modules/eco/node_modules/.bin/coffee
gears_eco/node_modules/eco/node_modules/coffee-script/.npmignore
gears_eco/node_modules/eco/node_modules/coffee-script/CNAME
gears_eco/node_modules/eco/node_modules/coffee-script/CONTRIBUTING.md
gears_eco/node_modules/eco/node_modules/coffee-script/LICENSE
gears_eco/node_modules/eco/node_modules/coffee-script/README
gears_eco/node_modules/eco/node_modules/coffee-script/Rakefile
gears_eco/node_modules/eco/node_modules/coffee-script/package.json
gears_eco/node_modules/eco/node_modules/coffee-script/bin/cake
gears_eco/node_modules/eco/node_modules/coffee-script/bin/coffee
gears_eco/node_modules/eco/node_modules/coffee-script/lib/coffee-script/browser.js
gears_eco/node_modules/eco/node_modules/coffee-script/lib/coffee-script/cake.js
gears_eco/node_modules/eco/node_modules/coffee-script/lib/coffee-script/coffee-script.js
gears_eco/node_modules/eco/node_modules/coffee-script/lib/coffee-script/command.js
gears_eco/node_modules/eco/node_modules/coffee-script/lib/coffee-script/grammar.js
gears_eco/node_modules/eco/node_modules/coffee-script/lib/coffee-script/helpers.js
