Metadata-Version: 1.1
Name: gears-eco
Version: 0.1
Summary: Eco: Embedded CoffeeScript templates for Gears
Home-page: UNKNOWN
Author: Eugene Cheltsov
Author-email: chill.icp@gmail.com
License: ISC
Keywords: gears django-gears gears-eco
Platform: UNKNOWN
Classifier: Development Status :: 3 - Alpha
Classifier: Intended Audience :: Developers
Classifier: License :: OSI Approved :: ISC License (ISCL)
Classifier: Operating System :: OS Independent
Classifier: Programming Language :: Python
Classifier: Programming Language :: Python :: 2.7
